automate_django/__init__.py
automate_django/automate_django.py
automate_django-0.2.dist-info/LICENSE
automate_django-0.2.dist-info/METADATA
automate_django-0.2.dist-info/WHEEL
automate_django-0.2.dist-info/top_level.txt
automate_django-0.2.dist-info/RECORD
