Metadata-Version: 2.1
Name: automate-django
Version: 0.2
Summary: Useful tool to create a static running django application Python
Home-page: https://github.com/khizaruddins/automate-django
Author: Syed Khizaruddin
Author-email: khizaruddins@gmail.com
License: MIT
Keywords: Django,Automation,DjangoAutomation,AutomateDjango,DjangoAutomate,AutomationDjango
Platform: UNKNOWN
Classifier: Development Status :: 4 - Beta
Classifier: Intended Audience :: Developers
Classifier: Topic :: Software Development :: Build Tools
Classifier: License :: OSI Approved :: MIT License
Classifier: Programming Language :: Python :: 3
Classifier: Programming Language :: Python :: 3.4
Classifier: Programming Language :: Python :: 3.5
Classifier: Programming Language :: Python :: 3.6
